copilot_lsp_bridge/__main__.py
copilot_lsp_bridge/__version__.py
copilot_lsp_bridge-0.0.3.dist-info/METADATA
copilot_lsp_bridge-0.0.3.dist-info/WHEEL
copilot_lsp_bridge-0.0.3.dist-info/entry_points.txt
copilot_lsp_bridge-0.0.3.dist-info/top_level.txt
copilot_lsp_bridge-0.0.3.dist-info/RECORD
