Metadata-Version: 2.4
Name: copilot-lsp-bridge
Version: 0.0.3
Summary: Add your description here
Requires-Python: >=3.13
Requires-Dist: advanced-aicode>=2.1.2
Requires-Dist: aider-install>=0.2.0
Requires-Dist: pygls>=1.3.1
Requires-Dist: pytest>=8.4.1
Requires-Dist: pytest-asyncio>=1.1.0
